[{"id":"6281575886399@s.whatsapp.net","healt":80},{"id":"12496030270@s.whatsapp.net","healt":70},{"id":"6289509960601@s.whatsapp.net","healt":90},{"id":"6289509960601@s.whatsapp.net","healt":100},{"id":"6289509960601@s.whatsapp.net","healt":100},{"id":"6289509960601@s.whatsapp.net","healt":100},{"id":"6289509960601@s.whatsapp.net","healt":100},{"id":"6289509960601@s.whatsapp.net","healt":100},{"id":"6289509960601@s.whatsapp.net","healt":100},{"id":"6289509960601@s.whatsapp.net","healt":190},{"id":"6287869116660@s.whatsapp.net","healt":-20},{"id":"6289509960601@s.whatsapp.net","healt":80},{"id":"6281929681799@s.whatsapp.net","healt":90},{"id":"6281929681799@s.whatsapp.net","healt":90},{"id":"6281929681799@s.whatsapp.net","healt":90},{"id":"6281929681799@s.whatsapp.net","healt":100},{"id":"6281929681799@s.whatsapp.net","healt":80},{"id":"6281929681799@s.whatsapp.net","healt":100},{"id":"6281929681799@s.whatsapp.net","healt":90},{"id":"17062149635@s.whatsapp.net","healt":100},{"id":"17062149635@s.whatsapp.net","healt":90},{"id":"6281361281833@s.whatsapp.net","healt":90},{"id":"6285361638309@s.whatsapp.net","healt":100},{"id":"6285361638309@s.whatsapp.net","healt":100},{"id":"6281361281833@s.whatsapp.net","healt":90},{"id":"6281361281833@s.whatsapp.net","healt":90}]